lambda_mcp/__init__.py
lambda_mcp/lambda_mcp.py
lambda_mcp/logging_config.py
lambda_mcp/request_handler.py
lambda_mcp/requests.py
lambda_mcp/response_builder.py
lambda_mcp/session.py
lambda_mcp/session_wrapper.py
lambda_mcp/tool_registry.py
lambda_mcp/types.py
actvalue_lambda_mcp_server-2.0.0.dist-info/METADATA
actvalue_lambda_mcp_server-2.0.0.dist-info/WHEEL
actvalue_lambda_mcp_server-2.0.0.dist-info/top_level.txt
actvalue_lambda_mcp_server-2.0.0.dist-info/RECORD
