Metadata-Version: 2.4
Name: actvalue.lambda-mcp-server
Version: 2.0.0
Summary: A Lambda-based MCP (Model Context Protocol) server implementation
Home-page: https://github.com/yourusername/lambda-mcp-server
Author: ActValue
License: MIT
Classifier: Development Status :: 4 - Beta
Classifier: Intended Audience :: Developers
Classifier: License :: OSI Approved :: MIT License
Classifier: Operating System :: OS Independent
Classifier: Programming Language :: Python :: 3
Classifier: Programming Language :: Python :: 3.12
Requires-Python: >=3.12
Requires-Dist: redis>=6.0.0
Requires-Dist: actvalue.aws-pysdk>=0.3.0
Provides-Extra: dev
Requires-Dist: boto3>=1.36.0; extra == "dev"
Requires-Dist: fastapi>=0.115.12; extra == "dev"
Requires-Dist: uvicorn>=0.34.2; extra == "dev"
Dynamic: home-page
Dynamic: requires-python
